jaynes/__init__.py
jaynes/client.py
jaynes/constants.py
jaynes/daemon.py
jaynes/entry.py
jaynes/gce_utils.py
jaynes/helpers.py
jaynes/jaynes.py
jaynes/mounts.py
jaynes/param_codec.py
jaynes/runners.py
jaynes/server.py
jaynes/shell.py
jaynes/templates.py
jaynes/launchers/__init__.py
jaynes/launchers/base_launcher.py
jaynes/launchers/ec2_launch.py
jaynes/launchers/gcp_launch.py
jaynes/launchers/kube_launch.py
jaynes/launchers/local_launcher.py
jaynes/launchers/manager_launch.py
jaynes/launchers/ssh_launch.py
jaynes/stale/__init__.py
jaynes-0.9.14.dist-info/LICENSE
jaynes-0.9.14.dist-info/METADATA
jaynes-0.9.14.dist-info/WHEEL
jaynes-0.9.14.dist-info/top_level.txt
jaynes-0.9.14.dist-info/RECORD
