Metadata-Version: 2.1
Name: jaynes
Version: 0.9.14
Summary: A tool for running python code with runner on aws
Home-page: https://github.com/episodeyang/jaynes
Author: Ge Yang
Author-email: yangge1987@gmail.com
License: Copyright 2022 Ge Yang
Requires-Dist: aiofile
Requires-Dist: cloudpickle (==3.1.1)
Requires-Dist: functional-notations
Requires-Dist: pyyaml
Requires-Dist: requests
Requires-Dist: termcolor
